opencitingpy/__init__.py
opencitingpy/classes.py
opencitingpy/client.py
opencitingpy/metadata.py
opencitingpy-0.1.1.dist-info/LICENSE
opencitingpy-0.1.1.dist-info/METADATA
opencitingpy-0.1.1.dist-info/WHEEL
opencitingpy-0.1.1.dist-info/top_level.txt
opencitingpy-0.1.1.dist-info/RECORD
