Metadata-Version: 2.1
Name: opencitingpy
Version: 0.1.1
Summary: Python tool for easily making requests to the OpenCitations API
Home-page: https://github.com/unaisaralegui/opencitingpy
Author: Unai Saralegui
Author-email: usaralegui@gmail.com
License: UNKNOWN
Platform: UNKNOWN
Classifier: Programming Language :: Python :: 3
Classifier: License :: OSI Approved :: MIT License
Classifier: Operating System :: OS Independent
Requires-Python: >=3.6
